axit/__init__.py
axit/mod1.py
axit-0.0.5.dist-info/LICENSE
axit-0.0.5.dist-info/METADATA
axit-0.0.5.dist-info/WHEEL
axit-0.0.5.dist-info/top_level.txt
axit-0.0.5.dist-info/RECORD
