Metadata-Version: 2.1
Name: axit
Version: 0.0.5
Summary: Axit is a package for ax things.
Home-page: https://github.com/kyshel/axit
Author: kyshel
Author-email: kyshel@example.com
License: UNKNOWN
Platform: UNKNOWN
Classifier: Programming Language :: Python :: 3
Classifier: License :: OSI Approved :: MIT License
Classifier: Operating System :: OS Independent
Requires-Python: >=3.6
